pyAutoAdaptiveRobustRegression/__init__.py
pyAutoAdaptiveRobustRegression/internal.py
pyAutoAdaptiveRobustRegression/bin/linux/pyAutoAdaptiveRobustRegression.so
pyAutoAdaptiveRobustRegression/bin/macos/pyAutoAdaptiveRobustRegression.dylib
pyAutoAdaptiveRobustRegression/bin/win32/libopenblas.dll
pyAutoAdaptiveRobustRegression/bin/win32/pyAutoAdaptiveRobustRegression.dll
pyAutoAdaptiveRobustRegression-0.1.3.dist-info/LICENSE
pyAutoAdaptiveRobustRegression-0.1.3.dist-info/METADATA
pyAutoAdaptiveRobustRegression-0.1.3.dist-info/WHEEL
pyAutoAdaptiveRobustRegression-0.1.3.dist-info/top_level.txt
pyAutoAdaptiveRobustRegression-0.1.3.dist-info/RECORD
