Metadata-Version: 2.1
Name: pyAutoAdaptiveRobustRegression
Version: 0.1.3
Summary: Auto Adaptive Robust Regression Python Package
Home-page: https://github.com/YichiZhang-Oxford/pyAutoAdaptiveRobustRegression
Author: Yichi Zhang
Author-email: yichi.zhang@worc.ox.ac.uk
License: MIT
Download-URL: https://github.com/YichiZhang-Oxford/pyAutoAdaptiveRobustRegression
Keywords: Auto Adaptive Robust Regression
Platform: UNKNOWN
Classifier: Development Status :: 3 - Alpha
Classifier: Intended Audience :: Developers
Classifier: Topic :: Software Development :: Build Tools
Classifier: License :: OSI Approved :: MIT License
Classifier: Programming Language :: Python :: 3
Classifier: Programming Language :: Python :: 3.4
Classifier: Programming Language :: Python :: 3.5
Classifier: Programming Language :: Python :: 3.6
Requires-Dist: numpy
